pgpc/__init__.py
pgpc/parser.py
pgpc/scanner.py
test/__init__.py
test/test_parse_text.py
pgpc-0.0.4.dist-info/LICENSE
pgpc-0.0.4.dist-info/METADATA
pgpc-0.0.4.dist-info/NOTICE
pgpc-0.0.4.dist-info/WHEEL
pgpc-0.0.4.dist-info/top_level.txt
pgpc-0.0.4.dist-info/RECORD
