Metadata-Version: 2.1
Name: pgpc
Version: 0.0.4
Summary: A Python Generator based Parser Combinator library
Home-page: https://github.com/neshkeev/pgpc
Author: neshkeev
Author-email: neshkeev@yandex.ru
License: Apache 2.0
Classifier: Development Status :: 3 - Alpha
Classifier: Intended Audience :: Developers
Classifier: Intended Audience :: Education
Classifier: License :: OSI Approved :: Apache Software License
Classifier: Operating System :: OS Independent
Classifier: Programming Language :: Python :: 3 :: Only
Classifier: Topic :: Software Development :: Libraries :: Python Modules
Classifier: Topic :: Text Processing :: General
Requires-Python: >=3.6
License-File: LICENSE
License-File: NOTICE
Provides-Extra: dev
Requires-Dist: pytest (>=7.0) ; extra == 'dev'
Requires-Dist: twine (>=4.0.2) ; extra == 'dev'
